dash_gridmap/DashGridmap.py
dash_gridmap/__init__.py
dash_gridmap/_imports_.py
dash_gridmap/dash_gridmap.min.js
dash_gridmap/dash_gridmap.min.js.map
dash_gridmap/metadata.json
dash_gridmap/package-info.json
dash_gridmap-0.0.1.dist-info/LICENSE
dash_gridmap-0.0.1.dist-info/METADATA
dash_gridmap-0.0.1.dist-info/WHEEL
dash_gridmap-0.0.1.dist-info/top_level.txt
dash_gridmap-0.0.1.dist-info/RECORD
